gxipy/DataStream.py
gxipy/Device.py
gxipy/DeviceManager.py
gxipy/Exception.py
gxipy/Feature.py
gxipy/FeatureControl.py
gxipy/Feature_s.py
gxipy/ImageFormatConvert.py
gxipy/ImageProc.py
gxipy/ImageProcess.py
gxipy/ImageProcessConfig.py
gxipy/Interface.py
gxipy/StatusProcessor.py
gxipy/__init__.py
gxipy/dxwrapper.py
gxipy/gxiapi.py
gxipy/gxidef.py
gxipy/gxwrapper.py
iai_gxipy-2.0.2407.9061.dist-info/LICENSE
iai_gxipy-2.0.2407.9061.dist-info/METADATA
iai_gxipy-2.0.2407.9061.dist-info/WHEEL
iai_gxipy-2.0.2407.9061.dist-info/top_level.txt
iai_gxipy-2.0.2407.9061.dist-info/RECORD
