Metadata-Version: 2.2
Name: iai-gxipy
Version: 2.0.2407.9061
Summary: Python API to use with the Daheng Imaging Galaxy SDK
Author: Daheng Imaging
License: MIT
Project-URL: Homepage, https://github.com/maximecharriere/gxipy
Classifier: Programming Language :: Python :: 3
Classifier: License :: OSI Approved :: MIT License
Classifier: Operating System :: OS Independent
Requires-Python: >=3.0
License-File: LICENSE
Requires-Dist: numpy
